jeddinformatics/.dirignore
jeddinformatics/.fileignore
jeddinformatics/__init__.py
jeddinformatics/__main__.py
jeddinformatics/config.json
jeddinformatics/convert_and_plot.py
jeddinformatics/generate_types.py
jeddinformatics/highchart_json_to_csv.py
jeddinformatics/oncodb_to_csv.py
jeddinformatics/plot_data.py
jeddinformatics/schema.json
jeddinformatics-0.7.0.dist-info/METADATA
jeddinformatics-0.7.0.dist-info/WHEEL
jeddinformatics-0.7.0.dist-info/licenses/LICENSE
jeddinformatics-0.7.0.dist-info/RECORD
