Metadata-Version: 2.3
Name: jeddinformatics
Version: 0.7.0
Summary: Convert bioinformatics data to plots
Project-URL: Homepage, https://github.com/wolffshots/jeddinformatics
Project-URL: Issues, https://github.com/wolffshots/jeddinformatics/issues
License-File: LICENSE
Keywords: bioinformatics,plotly
Classifier: Intended Audience :: Developers
Classifier: Operating System :: OS Independent
Classifier: Programming Language :: Python :: 3
Requires-Python: >=3.8
Requires-Dist: check-jsonschema>=0.28.0
Requires-Dist: datamodel-code-generator>=0.25.4
Requires-Dist: jsonschema>=4.21.1
Requires-Dist: kaleido==0.2.1
Requires-Dist: loguru>=0.7.2
Requires-Dist: openpyxl>=3.1.5
Requires-Dist: pandas>=2.2.1
Requires-Dist: plotly>=5.19.0
